{
	"info": {
		"_postman_id": "f9a99c68-212e-478a-a24b-83b3b4deb155",
		"name": "Assignment 6 Backend",
		"schema": "https://schema.getpostman.com/json/collection/v2.1.0/collection.json",
		"_exporter_id": "39749761"
	},
	"item": [
		{
			"name": "Users",
			"item": [
				{
					"name": "Create Student",
					"request": {
						"method": "POST",
						"header": [],
						"body": {
							"mode": "raw",
							"raw": "{\n    \"password\": \"12345678\",\n    \"student\": {\n        \"name\": \"John Doe\",\n        \"email\": \"student1@gmail.com\",\n        \"gender\": \"male\",\n        \"dateOfBirth\": \"2000-05-15T00:00:00.000Z\",\n        \"contactNo\": \"01712345678\",\n        \"emergencyContactNo\": \"01812345678\",\n        \"bloodGroup\": \"A+\",\n        \"presentAddress\": \"123 Main Street, Dhaka\",\n        \"permanentAddress\": \"456 Village Road, Khulna\",\n        \"profileImg\": \"https://example.com/images/profile.jpg\",\n        \"coverImg\": \"https://example.com/images/cover.jpg\",\n        \"isDeleted\": false\n    }\n}",
							"options": {
								"raw": {
									"language": "json"
								}
							}
						},
						"url": {
							"raw": "http://localhost:5000/api/users/create-student",
							"protocol": "http",
							"host": [
								"localhost"
							],
							"port": "5000",
							"path": [
								"api",
								"users",
								"create-student"
							]
						}
					},
					"response": []
				},
				{
					"name": "create teacher",
					"request": {
						"method": "POST",
						"header": [],
						"body": {
							"mode": "raw",
							"raw": "{\n    \"password\": \"12345678\",\n    \"teacher\": {\n        \"name\": \"Karim Uddin\",\n        \"email\": \"teacher2@gmail.com\",\n        \"gender\": \"male\",\n        \"dateOfBirth\": \"1985-06-15T00:00:00.000Z\",\n        \"user\": \"661190abf3c8a7b9de2a5e8f\",\n        \"contactNo\": \"01712345678\",\n        \"emergencyContactNo\": \"01898765432\",\n        \"bloodGroup\": \"O+\",\n        \"designation\": \"Senior Lecturer\",\n        \"bio\": \"Passionate physics teacher with over 10 years of experience in guiding students towards academic excellence.\",\n        \"subjects\": [\n            \"Physics\",\n            \"Mathematics\",\n            \"Higher Mathematics\"\n        ],\n        \"district\": \"dhaka\",\n        \"presentAddress\": \"House #10, Road #5, Dhanmondi, Dhaka\",\n        \"permanentAddress\": \"Village: Charigram, Upazila: Singair, District: Manikganj\",\n        \"profileImg\": \"https://example.com/images/rahim-profile.jpg\",\n        \"coverImg\": \"https://example.com/images/rahim-cover.jpg\",\n        \"isDeleted\": false\n    }\n}",
							"options": {
								"raw": {
									"language": "json"
								}
							}
						},
						"url": {
							"raw": "http://localhost:5000/api/users/create-teacher",
							"protocol": "http",
							"host": [
								"localhost"
							],
							"port": "5000",
							"path": [
								"api",
								"users",
								"create-teacher"
							]
						}
					},
					"response": []
				}
			]
		},
		{
			"name": "Auth",
			"item": [
				{
					"name": "Login User",
					"request": {
						"method": "POST",
						"header": [],
						"body": {
							"mode": "raw",
							"raw": "{\n    \"email\" : \"student1@gmail.com\",\n    \"password\" : \"12345678\"\n}",
							"options": {
								"raw": {
									"language": "json"
								}
							}
						},
						"url": {
							"raw": "http://localhost:5000/api/auth/login",
							"protocol": "http",
							"host": [
								"localhost"
							],
							"port": "5000",
							"path": [
								"api",
								"auth",
								"login"
							]
						}
					},
					"response": []
				},
				{
					"name": "Refresh Token",
					"request": {
						"method": "POST",
						"header": [],
						"body": {
							"mode": "raw",
							"raw": "{\n    \"email\" : \"student1@gmail.com\",\n    \"password\" : \"12345678\"\n}",
							"options": {
								"raw": {
									"language": "json"
								}
							}
						},
						"url": {
							"raw": "http://localhost:5000/api/auth/login",
							"protocol": "http",
							"host": [
								"localhost"
							],
							"port": "5000",
							"path": [
								"api",
								"auth",
								"login"
							]
						}
					},
					"response": []
				}
			]
		},
		{
			"name": "Reviews",
			"item": [
				{
					"name": "create review",
					"request": {
						"method": "POST",
						"header": [],
						"body": {
							"mode": "raw",
							"raw": "{\n  \"teacher\": \"67f2c0e471efcda488910b81\",\n  \"student\": \"67f37943618d6d0c53e3a1f6\",\n  \"comment\": \"Great tutor! 2nd reviews\",\n  \"rating\": 5,\n  \"review\": \"He explained quantum mechanics in a really simple way. Very impressive.\"\n}\n",
							"options": {
								"raw": {
									"language": "json"
								}
							}
						},
						"url": {
							"raw": "http://localhost:5000/api/reviews",
							"protocol": "http",
							"host": [
								"localhost"
							],
							"port": "5000",
							"path": [
								"api",
								"reviews"
							]
						}
					},
					"response": []
				}
			]
		},
		{
			"name": "Teachers",
			"item": [
				{
					"name": "getAllTeachers",
					"request": {
						"method": "GET",
						"header": []
					},
					"response": []
				},
				{
					"name": "getSingleTeacher",
					"request": {
						"method": "GET",
						"header": []
					},
					"response": []
				},
				{
					"name": "TurnOnAvability",
					"request": {
						"method": "PATCH",
						"header": [],
						"url": {
							"raw": "http://localhost:5000/api/teachers/avabilityStatusOn/67f60e8f5bf5402040621753",
							"protocol": "http",
							"host": [
								"localhost"
							],
							"port": "5000",
							"path": [
								"api",
								"teachers",
								"avabilityStatusOn",
								"67f60e8f5bf5402040621753"
							]
						}
					},
					"response": []
				},
				{
					"name": "TurnOfAvability",
					"request": {
						"method": "PATCH",
						"header": [],
						"url": {
							"raw": "http://localhost:5000/api/teachers/avabilityStatusOn/67f60e8f5bf5402040621753",
							"protocol": "http",
							"host": [
								"localhost"
							],
							"port": "5000",
							"path": [
								"api",
								"teachers",
								"avabilityStatusOn",
								"67f60e8f5bf5402040621753"
							]
						}
					},
					"response": []
				},
				{
					"name": "update Hourly Rate",
					"request": {
						"method": "PATCH",
						"header": [
							{
								"key": "Authorization",
								"value": "eyJhbGciOiJIUzI1NiIsInR5cCI6IkpXVCJ9.eyJ1c2VyRW1haWwiOiJzdHVkZW50MUBnbWFpbC5jb20iLCJyb2xlIjoic3R1ZGVudCIsInVzZXJJZCI6IjY3ZjYxZTQ4MzVhZjdlOWM5ZDk0MzFlMCIsImlhdCI6MTc0NDE4MzMzOSwiZXhwIjoxNzQ0Nzg4MTM5fQ.LR8NziuumYSrNXT7W8bQuHQthsRIEULGrwo6RfbyXS0",
								"type": "text"
							}
						],
						"body": {
							"mode": "raw",
							"raw": "{\n    \"hourlyRate\": 250\n}",
							"options": {
								"raw": {
									"language": "json"
								}
							}
						},
						"url": {
							"raw": "http://localhost:5000/api/teachers/hourlyRate/67f61673ef3318102f15059e",
							"protocol": "http",
							"host": [
								"localhost"
							],
							"port": "5000",
							"path": [
								"api",
								"teachers",
								"hourlyRate",
								"67f61673ef3318102f15059e"
							]
						}
					},
					"response": []
				}
			]
		},
		{
			"name": "Bookings",
			"item": [
				{
					"name": "Create Bookings",
					"request": {
						"method": "POST",
						"header": [],
						"body": {
							"mode": "raw",
							"raw": "{\n  \"teacher\": \"642b1f2fa56e3a001c8d2f4a\",\n  \"student\": \"642b1f3fa56e3a001c8d2f4b\",\n  \"days\": [\"Mon\", \"Wed\", \"Fri\"],\n  \"startTime\": \"15:00\",\n  \"endTime\": \"16:30\",\n  \"duration\": 50\n}\n",
							"options": {
								"raw": {
									"language": "json"
								}
							}
						},
						"url": {
							"raw": "http://localhost:5000/api/bookings",
							"protocol": "http",
							"host": [
								"localhost"
							],
							"port": "5000",
							"path": [
								"api",
								"bookings"
							]
						}
					},
					"response": []
				},
				{
					"name": "get All Bookings",
					"protocolProfileBehavior": {
						"disableBodyPruning": true
					},
					"request": {
						"method": "GET",
						"header": [],
						"body": {
							"mode": "raw",
							"raw": "{\n  \"teacher\": \"642b1f2fa56e3a001c8d2f4a\",\n  \"student\": \"642b1f3fa56e3a001c8d2f4b\",\n  \"days\": [\"Mon\", \"Wed\", \"Fri\"],\n  \"startTime\": \"15:00\",\n  \"endTime\": \"16:30\",\n  \"duration\": 50\n}\n",
							"options": {
								"raw": {
									"language": "json"
								}
							}
						},
						"url": {
							"raw": "http://localhost:5000/api/bookings",
							"protocol": "http",
							"host": [
								"localhost"
							],
							"port": "5000",
							"path": [
								"api",
								"bookings"
							]
						}
					},
					"response": []
				}
			]
		}
	]
}